{
  "meta": {
    "date": "2026-03-27",
    "edition": "晨风早报 · 第 128 期",
    "greeting": "早安，新的一天从掌握市场脉搏开始。"
  },
  "overallSentiment": {
    "emoji": "⛅",
    "phrase": "今日整体偏谨慎"
  },
  "todayHighlights": [
    {
      "id": 1,
      "emoji": "🏦",
      "title": "美联储维持利率不变",
      "summary": "美联储3月议息会议决定维持联邦基金利率在4.25%-4.50%区间不变，符合市场预期。鲍威尔表示将继续关注通胀数据，暗示年内降息窗口可能推迟至下半年。"
    },
    {
      "id": 2,
      "emoji": "🇨🇳",
      "title": "国务院发布新一轮消费刺激政策",
      "summary": "国务院常务会议审议通过《关于进一步释放消费潜力的若干措施》，涉及家电以旧换新补贴扩容、新能源汽车下乡、以及数字消费券发放等多项举措，预计拉动消费超3000亿元。"
    },
    {
      "id": 3,
      "emoji": "💊",
      "title": "国家医保局公布新版药品目录",
      "summary": "2026年版国家医保药品目录新增67种药品，其中创新药占比超60%。多款国产PD-1抑制剂、ADC药物纳入目录，利好国内创新药企。"
    }
  ],
  "globalMarkets": [
    {
      "name": "上证指数",
      "code": "000001.SS",
      "price": 3285.67,
      "change": 1.23,
      "region": "cn",
      "sparkline": [3210, 3225, 3240, 3238, 3260, 3272, 3286]
    },
    {
      "name": "深证成指",
      "code": "SZ399001",
      "price": 10456.32,
      "change": 1.58,
      "region": "cn",
      "sparkline": [10200, 10280, 10310, 10350, 10380, 10420, 10456]
    },
    {
      "name": "创业板指",
      "code": "SZ399006",
      "price": 2134.89,
      "change": 2.15,
      "region": "cn",
      "sparkline": [2050, 2070, 2085, 2090, 2100, 2118, 2135]
    },
    {
      "name": "恒生指数",
      "code": "HSI",
      "price": 22876.45,
      "change": -0.34,
      "region": "hk",
      "sparkline": [23100, 23050, 22980, 22950, 22920, 22900, 22876]
    },
    {
      "name": "道琼斯",
      "code": "DJI",
      "price": 42567.89,
      "change": 0.45,
      "region": "us",
      "sparkline": [42200, 42350, 42300, 42400, 42450, 42500, 42568]
    },
    {
      "name": "纳斯达克",
      "code": "IXIC",
      "price": 18234.56,
      "change": -0.78,
      "region": "us",
      "sparkline": [18500, 18450, 18380, 18350, 18300, 18270, 18235]
    },
    {
      "name": "标普500",
      "code": "SPX",
      "price": 5678.12,
      "change": 0.22,
      "region": "us"
    },
    {
      "name": "日经225",
      "code": "N225",
      "price": 40123.67,
      "change": -1.12,
      "region": "jp"
    },
    {
      "name": "美元/人民币",
      "code": "USDCNY",
      "price": 7.1823,
      "change": -0.15,
      "region": "fx"
    },
    {
      "name": "布伦特原油",
      "code": "BRENT",
      "price": 82.45,
      "change": 1.87,
      "region": "commodity"
    },
    {
      "name": "COMEX黄金",
      "code": "GOLD",
      "price": 3045.30,
      "change": 0.56,
      "region": "commodity"
    },
    {
      "name": "比特币",
      "code": "BTC",
      "price": 87654.32,
      "change": -2.34,
      "region": "crypto"
    }
  ],
  "macroPulse": [
    {
      "id": 1,
      "title": "中国2月PMI回升至50.2",
      "summary": "国家统计局数据显示，2月制造业PMI为50.2%，重回荣枯线上方，环比上升0.5个百分点。新订单指数和生产指数双双回升，显示经济复苏动能增强。",
      "tag": "数据",
      "sentiment": "positive"
    },
    {
      "id": 2,
      "title": "美国CPI同比上涨2.8%",
      "summary": "美国劳工部公布2月CPI数据，同比上涨2.8%，略高于市场预期的2.7%。核心CPI同比上涨3.1%，通胀黏性仍存，市场对美联储降息预期进一步推迟。",
      "tag": "通胀",
      "sentiment": "negative"
    },
    {
      "id": 3,
      "title": "欧央行暗示4月可能再次降息",
      "summary": "欧洲央行行长拉加德在讲话中表示，欧元区通胀正在按预期回落，如果经济数据继续支持，4月会议将考虑进一步下调利率。欧元兑美元小幅走低。",
      "tag": "央行",
      "sentiment": "neutral"
    },
    {
      "id": 4,
      "title": "中国社融数据超预期",
      "summary": "2月新增社会融资规模2.23万亿元，高于市场预期的1.95万亿。其中企业中长期贷款增加明显，反映实体经济融资需求回暖。",
      "tag": "信贷",
      "sentiment": "positive"
    }
  ],
  "overseasPerspective": [
    {
      "id": 1,
      "source": "华尔街日报",
      "title": "科技巨头AI军备竞赛进入新阶段",
      "summary": "微软、谷歌、Meta三大科技巨头本季度AI资本开支合计超过500亿美元，创历史新高。分析师担忧AI投资回报周期过长，但各公司高管表示「投资不足的风险远大于投资过度」。",
      "region": "美国",
      "publishedAt": "2026-03-27T02:30:00Z"
    },
    {
      "id": 2,
      "source": "金融时报",
      "title": "日本央行考虑加速退出YCC",
      "summary": "据金融时报援引知情人士消息，日本央行正在讨论在4月会议上进一步调整收益率曲线控制政策，可能将10年期国债收益率目标上限提升至1.5%。日元汇率短线走强。",
      "region": "日本",
      "publishedAt": "2026-03-26T22:15:00Z"
    },
    {
      "id": 3,
      "source": "路透社",
      "title": "OPEC+减产协议面临分歧",
      "summary": "沙特与阿联酋在减产配额分配上出现分歧，市场担忧OPEC+团结出现裂痕。分析人士认为，若减产协议松动，油价短期可能承压回调至75-78美元区间。",
      "region": "中东",
      "publishedAt": "2026-03-26T18:45:00Z"
    }
  ],
  "industryFocus": {
    "healthcare": {
      "title": "医疗健康",
      "icon": "💊",
      "highlights": [
        {
          "id": 1,
          "title": "创新药出海再获突破",
          "summary": "百济神州泽布替尼在欧洲获批第三个适应症，全球销售额有望突破30亿美元。同时，信达生物PD-1/VEGF双抗在美国FDA获得优先审评资格。",
          "sentiment": "positive",
          "publishedAt": "2026-03-27T01:00:00Z"
        },
        {
          "id": 2,
          "title": "医疗器械集采扩面",
          "summary": "第四批国家医疗器械集采品种名单公布，涉及人工关节、脊柱耗材等8个品类。市场预计平均降幅在50%-70%，相关企业短期业绩承压。",
          "sentiment": "negative",
          "publishedAt": "2026-03-26T23:30:00Z"
        }
      ]
    },
    "energy": {
      "title": "能源",
      "icon": "⚡",
      "highlights": [
        {
          "id": 1,
          "title": "光伏行业拐点信号显现",
          "summary": "工信部发布光伏行业规范条件（2026年版），提高新建产能门槛。多家头部企业宣布减产计划，行业供需格局有望在下半年改善。硅料价格本周小幅反弹3.2%。",
          "sentiment": "positive",
          "publishedAt": "2026-03-27T03:00:00Z"
        },
        {
          "id": 2,
          "title": "全国碳市场扩容在即",
          "summary": "生态环境部表示将在年内把钢铁、水泥、铝冶炼行业纳入全国碳排放交易市场，覆盖排放量将占全国总量的60%以上。碳配额价格近期持续走高至95元/吨。",
          "sentiment": "positive",
          "publishedAt": "2026-03-26T20:00:00Z"
        }
      ]
    }
  },
  "premarketSignals": [
    {
      "id": 1,
      "category": "北向资金",
      "signal": "昨日净流入42.6亿元，连续第5个交易日净流入，累计流入超180亿元",
      "direction": "bullish"
    },
    {
      "id": 2,
      "category": "融资余额",
      "signal": "两市融资余额升至1.85万亿元，创近6个月新高",
      "direction": "bullish"
    },
    {
      "id": 3,
      "category": "隔夜中概",
      "signal": "纳斯达克中国金龙指数跌1.2%，阿里巴巴跌2.3%，京东跌1.8%",
      "direction": "bearish"
    },
    {
      "id": 4,
      "category": "A50期货",
      "signal": "富时中国A50期货夜盘收涨0.35%，暗示A股小幅高开",
      "direction": "bullish"
    },
    {
      "id": 5,
      "category": "关键事件",
      "signal": "今日将公布2月工业企业利润数据，市场预期同比增长6.5%",
      "direction": "neutral"
    }
  ]
}
